main.py
eb_mcp-0.1.0.dist-info/METADATA
eb_mcp-0.1.0.dist-info/WHEEL
eb_mcp-0.1.0.dist-info/top_level.txt
eb_mcp-0.1.0.dist-info/RECORD
