Metadata-Version: 2.4
Name: eb-mcp
Version: 0.1.0
Summary: Add your description here
Requires-Python: >=3.13
Requires-Dist: boto3>=1.37.38
Requires-Dist: mcp[cli]>=1.6.0
Requires-Dist: python-dotenv>=1.1.0
